magma_multigas/__init__.py
magma_multigas/diagnose.py
magma_multigas/multigas.py
magma_multigas/multigas_data.py
magma_multigas/plot.py
magma_multigas/plot_availability.py
magma_multigas/plot_var.py
magma_multigas/plot_wind_direction.py
magma_multigas/query.py
magma_multigas/utilities.py
magma_multigas/validator.py
magma_multigas/variables.py
magma_multigas/plotly_calplot/__init__.py
magma_multigas/plotly_calplot/calplot.py
magma_multigas/plotly_calplot/date_extractors.py
magma_multigas/plotly_calplot/layout_formatter.py
magma_multigas/plotly_calplot/raw_heatmap.py
magma_multigas/plotly_calplot/single_year_calplot.py
magma_multigas/plotly_calplot/utils.py
magma_multigas/resources/__init__.py
magma_multigas/resources/colors.py
magma_multigas/resources/columns_explanations.csv
magma_multigas/resources/material-colors.json
magma_multigas/resources/metadata_v4.xml
magma_multigas-1.5.0.dist-info/licenses/LICENSE
magma_multigas-1.5.0.dist-info/WHEEL
magma_multigas-1.5.0.dist-info/METADATA
magma_multigas-1.5.0.dist-info/RECORD
