Metadata-Version: 2.4
Name: magma-multigas
Version: 1.5.0
Summary: MultiGas package for internal use. A collaboration between CVGHM and USGS
Keywords: gas,volcano,multigas,usgs,cvghm,pvmbg
Author-email: Martanto <martanto@live.com>
Requires-Python: >=3.11
Classifier: License :: OSI Approved :: MIT License
Classifier: Operating System :: OS Independent
Classifier: Programming Language :: Python :: 3.11
Classifier: Programming Language :: Python :: 3.12
License-File: LICENSE
Requires-Dist: openpyxl>=3.1.5
Requires-Dist: pandas>=2.2.2
Requires-Dist: numpy>=2.2.5
Requires-Dist: matplotlib>=3.9.0
Requires-Dist: magma-auth>=1.0.0
Requires-Dist: magma-var>=0.1.0
Requires-Dist: pytz>=2024.1
Requires-Dist: kaleido
Requires-Dist: plotly>=5.23.0
Requires-Dist: windrose
Requires-Dist: seaborn
Requires-Dist: importlib-resources
Requires-Dist: openpyxl>=3.1.0 ; extra == "base"
Requires-Dist: numpy>=2.0.0 ; extra == "base"
Requires-Dist: pandas>=2.2.2 ; extra == "base"
Requires-Dist: matplotlib>=3.9.0 ; extra == "base"
Requires-Dist: seaborn>=0.13.2 ; extra == "base"
Requires-Dist: windrose ; extra == "base"
Project-URL: Homepage, https://github.com/martanto/magma-multigas
Project-URL: Issues, https://github.com/martanto/magma-multigas/issues
Provides-Extra: base
